{"guid":["https://github.com/artem-zinnatullin/TheContext-Podcast/releases/download/Episode_1/The.Context.episode.1.mp3"],"title":["Episode 1, Architecture of modern Android apps with Hannes Dorfmann"],"link":["https://github.com/artem-zinnatullin/TheContext-Podcast/blob/master/show_notes/Episode_1.md"],"atom:link":[{"$":{"rel":"replies","type":"text/html","href":"https://github.com/artem-zinnatullin/TheContext-Podcast/issues/1"}}],"itunes:duration":["57:55"],"pubDate":["Thu, 04 Feb 2016 20:04:07 PST"],"enclosure":[{"$":{"url":"https://github.com/artem-zinnatullin/TheContext-Podcast/releases/download/Episode_1/The.Context.episode.1.mp3","length":"83400224","type":"audio/mpeg"}}],"atom:contributor":[{"atom:name":["Hannes Dorfmann"],"atom:uri":["http://hannesdorfmann.com/"]}],"atom:author":[{"atom:name":["Artem Zinnatullin"],"atom:uri":["http://artemzin.com/"],"atom:email":["artem.zinnatullin@gmail.com"]}],"itunes:summary":["\n\t\t\t\n\t\t\t<h1>Episode 1: Architecture of modern Android apps</h1>\n\n\n\n\t\t\t<p>In this episode we have talked about software architecture on Android. We have covered:</p>\n\n\t\t\t<ul>\n\t\t\t\t<li>MVC</li>\n\t\t\t\t<li>MVVM</li>\n\t\t\t\t<li>MVVMC</li>\n\t\t\t\t<li>MVP</li>\n\t\t\t\t<li><a href=\"https://facebook.github.io/flux/docs/overview.html\">Flux</a></li>\n\t\t\t\t<li><a href=\"http://cycle.js.org/\">Cycle.js</a> (a.k.a. Model-View-Intent)</li>\n\t\t\t</ul>\n\n\t\t\t<h4>Guest:</h4>\n\n\t\t\t<p>Hannes Dorfmann <a href=\"https://twitter.com/sockeqwe\">@sockeqwe</a>, <a href=\"http://hannesdorfmann.com/\">personal blog</a>, <a href=\"https://github.com/sockeqwe/\">GitHub</a></p>\n\n\t\t\t<p>Open Source projects from Hannes:</p>\n\n\t\t\t<ul>\n\t\t\t\t<li><a href=\"https://github.com/sockeqwe/mosby\">Mosby</a></li>\n\t\t\t\t<li><a href=\"https://github.com/sockeqwe/sqlbrite-dao\">SQLBrite-DAO</a></li>\n\t\t\t\t<li><a href=\"https://github.com/sockeqwe/fragmentargs\">FragmentArgs</a></li>\n\t\t\t\t<li><a href=\"https://github.com/sockeqwe/ParcelablePlease\">ParcelablePlease</a></li>\n\t\t\t</ul>\n\n\t\t\t<h4>Additional links</h4>\n\n\t\t\t<ul>\n\t\t\t\t<li><a href=\"https://github.com/google/auto/issues/268\">AutoValue split into 2 jars issue</a></li>\n\t\t\t\t<li><a href=\"https://google.github.io/dagger/testing.html\">Dagger 2 document about testing</a></li>\n\t\t\t\t<li><a href=\"https://github.com/rheinfabrik/android-mvvm-example\">Clean MVVM example</a></li>\n\t\t\t\t<li><a href=\"https://github.com/google/dagger/issues/298\">Gradle's incremental build issue with annotation processing</a></li>\n\t\t\t</ul>\n\t\t\n\t\t"]}